doCheck/__init__.py
doCheck/checkers.py
doCheck-0.1.3.dist-info/LICENSE
doCheck-0.1.3.dist-info/METADATA
doCheck-0.1.3.dist-info/WHEEL
doCheck-0.1.3.dist-info/top_level.txt
doCheck-0.1.3.dist-info/RECORD
