Metadata-Version: 2.1
Name: doCheck
Version: 0.1.3
Summary: Check the value both type and value and then constraint it.
Home-page: https://kuankuan2007.gitee.io/do-check-pages/
Author: kuankuan
Author-email: 2163826131@qq.com
License: Mulan PSL v2
Keywords: type,check,value,constraint
Platform: windows
Platform: linux
Platform: macos
Classifier: Natural Language :: English
Classifier: Development Status :: 4 - Beta
Classifier: Intended Audience :: Developers
Classifier: Programming Language :: Python :: 3
Classifier: Operating System :: MacOS
Classifier: Operating System :: POSIX :: Linux
Classifier: Operating System :: Microsoft :: Windows
Classifier: License :: OSI Approved :: Mulan Permissive Software License v2 (MulanPSL-2.0)
License-File: LICENSE
